.VERSION
AUTHORS.rst
CONTRIBUTING.rst
HISTORY.rst
LICENSE
MANIFEST.in
Pipfile
Pipfile.lock
README.rst
USAGE.rst
dev-requirements.txt
requirements.txt
setup.cfg
setup.py
docs/Makefile
docs/authors.rst
docs/conf.py
docs/contributing.rst
docs/history.rst
docs/index.rst
docs/installation.rst
docs/readme.rst
docs/usage.rst
mapscookiegettercli/.VERSION
mapscookiegettercli/AUTHORS.rst
mapscookiegettercli/CONTRIBUTING.rst
mapscookiegettercli/HISTORY.rst
mapscookiegettercli/LICENSE
mapscookiegettercli/Pipfile
mapscookiegettercli/Pipfile.lock
mapscookiegettercli/README.rst
mapscookiegettercli/USAGE.rst
mapscookiegettercli/__init__.py
mapscookiegettercli/_version.py
mapscookiegettercli/dev-requirements.txt
mapscookiegettercli/mapscookiegettercli.py
mapscookiegettercli/mapscookiegettercliexceptions.py
mapscookiegettercli/requirements.txt
mapscookiegettercli.egg-info/PKG-INFO
mapscookiegettercli.egg-info/SOURCES.txt
mapscookiegettercli.egg-info/dependency_links.txt
mapscookiegettercli.egg-info/entry_points.txt
mapscookiegettercli.egg-info/not-zip-safe
mapscookiegettercli.egg-info/requires.txt
mapscookiegettercli.egg-info/top_level.txt
mapscookiegettercli/__pycache__/__init__.cpython-37.pyc
mapscookiegettercli/__pycache__/_version.cpython-37.pyc
mapscookiegettercli/__pycache__/mapscookiegettercli.cpython-37.pyc
mapscookiegettercli/__pycache__/mapscookiegettercliexceptions.cpython-37.pyc
mapscookiegettercli/browsers/__init__.py
mapscookiegettercli/browsers/chrome.py
mapscookiegettercli/browsers/edge.py
mapscookiegettercli/browsers/firefox.py
mapscookiegettercli/browsers/ie.py
mapscookiegettercli/browsers/__pycache__/__init__.cpython-37.pyc
mapscookiegettercli/browsers/__pycache__/chrome.cpython-37.pyc
mapscookiegettercli/browsers/__pycache__/edge.cpython-37.pyc
mapscookiegettercli/browsers/__pycache__/firefox.cpython-37.pyc
mapscookiegettercli/browsers/__pycache__/ie.cpython-37.pyc
mapscookiegettercli/drivers/chromedriver_2.46
mapscookiegettercli/library/__init__.py
mapscookiegettercli/library/cookiegetter.py
mapscookiegettercli/library/__pycache__/__init__.cpython-37.pyc
mapscookiegettercli/library/__pycache__/cookiegetter.cpython-37.pyc