Metadata-Version: 1.1
Name: mapscookiegettercli
Version: 0.2.0
Summary: A tool to retreive the cookies from a google authentication process towards the google maps service to be used with locationsharinglib.
Home-page: https://github.com/costastf/mapscookiegettercli
Author: Costas Tyfoxylos
Author-email: costas.tyf@gmail.com
License: MIT
Keywords: mapscookiegettercli location sharing google maps retrieve cookies
Platform: UNKNOWN
Classifier: Development Status :: 4 - Beta
Classifier: Intended Audience :: Developers
Classifier: License :: OSI Approved :: MIT License
Classifier: Natural Language :: English
Classifier: Programming Language :: Python :: 3.7
